corsair/__init__.py
corsair/__main__.py
corsair/_version.py
corsair/bitfield.py
corsair/config.py
corsair/enum.py
corsair/generators.py
corsair/reg.py
corsair/regmap.py
corsair/utils.py
corsair/templates/amm2lb_verilog.j2
corsair/templates/amm2lb_vhdl.j2
corsair/templates/apb2lb_verilog.j2
corsair/templates/apb2lb_vhdl.j2
corsair/templates/axil2lb_verilog.j2
corsair/templates/axil2lb_vhdl.j2
corsair/templates/c_header.j2
corsair/templates/regmap_asciidoc.j2
corsair/templates/regmap_md.j2
corsair/templates/regmap_py.j2
corsair/templates/regmap_verilog.j2
corsair/templates/regmap_vhdl.j2
corsair/templates/sv_package.j2
corsair/templates/verilog_header.j2
corsair-1.0.4.dist-info/LICENSE.txt
corsair-1.0.4.dist-info/METADATA
corsair-1.0.4.dist-info/WHEEL
corsair-1.0.4.dist-info/entry_points.txt
corsair-1.0.4.dist-info/top_level.txt
corsair-1.0.4.dist-info/RECORD
