Metadata-Version: 2.1
Name: corsair
Version: 1.0.4
Summary: Control and Status Register map generator for FPGA/ASIC projects
Home-page: https://github.com/esynr3z/corsair
Author: esynr3z
Author-email: esynr3z@gmail.com
Project-URL: Documentation, https://corsair.readthedocs.io
Classifier: Programming Language :: Python :: 3
Classifier: License :: OSI Approved :: MIT License
Classifier: Operating System :: OS Independent
Requires-Python: >=3.6
License-File: LICENSE.txt
Requires-Dist: pyyaml (>=5.1)
Requires-Dist: jinja2
Requires-Dist: wavedrom
